Metadata-Version: 2.1
Name: ScalableWriter
Version: 1.2.1
Summary: Generate SVG code on a programmatic way.
Home-page: https://github.com/ZSendokame/Scalable
Author: ZSendokame
License: MIT license
Platform: UNKNOWN
License-File: LICENSE
